dallecli/__init__.py
dallecli/cli.py
dallecli-2.2.0.dist-info/LICENSE
dallecli-2.2.0.dist-info/METADATA
dallecli-2.2.0.dist-info/WHEEL
dallecli-2.2.0.dist-info/entry_points.txt
dallecli-2.2.0.dist-info/top_level.txt
dallecli-2.2.0.dist-info/RECORD
