Metadata-Version: 2.1
Name: dallecli
Version: 2.2.0
Summary: A command line application to help wrap the OpenAI Dalle 3 api and other utilities.
Home-page: https://github.com/raiyanyahya/dallecli
Author: Raiyan Yahya
Author-email: raiyanyahyadeveloper@gmail.com
License: MIT
Keywords: cli,developer tools,productivity,openai,generative art,ai
Platform: UNKNOWN
Requires-Python: >3.8
Requires-Dist: requests ==2.31.0
Requires-Dist: click ==8.1.3
Requires-Dist: openai ==1.6.1
Requires-Dist: rich ==13.4.2
Requires-Dist: idna
Requires-Dist: pillow ==10.0.1
